{
    "ПансіонатДачаБекетова2*": {
        "name": "ПансіонатДачаБекетова2*",
        "url": "https://www.turpravda.ua/uc/alushta/Pansionat_Dacha_Beketova-h87189.html",
        "rate": "8.1",
        "city": "Крим,\nАлушта",
        "service": "БезкоштовнийWi-Fi,\nВласнийпляж,\nСпа/велнес"
    },
    "РезиденціяКримськийБриз5*": {
        "name": "РезиденціяКримськийБриз5*",
        "url": "https://www.turpravda.ua/uc/yalta/Krymskiy_Briz-h35077.html",
        "rate": "8.1",
        "city": "Крим,\nАлушта",
        "service": "БезкоштовнийWi-Fi,\nВласнийпляж,\nСпа/велнес"
    },
    "Sunrise4*": {
        "name": "Sunrise4*",
        "url": "https://www.turpravda.ua/uc/feodosia/Sunrise-h21650.html",
        "rate": "8.1",
        "city": "Крим,\nАлушта",
        "service": "БезкоштовнийWi-Fi,\nВласнийпляж,\nСпа/велнес"
    },
    "Рига3*": {
        "name": "Рига3*",
        "url": "https://www.turpravda.ua/uc/schjolkino/Riga-h22092.html",
        "rate": "8.1",
        "city": "Крим,\nАлушта",
        "service": "БезкоштовнийWi-Fi,\nВласнийпляж,\nСпа/велнес"
    },
    "Зоря1*": {
        "name": "Зоря1*",
        "url": "https://www.turpravda.ua/uc/kerch/Zarja-h14944.html",
        "rate": "8.1",
        "city": "Крим,\nАлушта",
        "service": "БезкоштовнийWi-Fi,\nВласнийпляж,\nСпа/велнес"
    },
    "ДельМар3*": {
        "name": "ДельМар3*",
        "url": "https://www.turpravda.ua/uc/evpatoria/delmar-h56176.html",
        "rate": "8.1",
        "city": "Крим,\nАлушта",
        "service": "БезкоштовнийWi-Fi,\nВласнийпляж,\nСпа/велнес"
    },
    "Парк-готельРоманова3*": {
        "name": "Парк-готельРоманова3*",
        "url": "https://www.turpravda.ua/uc/evpatoria/Park_Otel_Romanova-h83238.html",
        "rate": "8.1",
        "city": "Крим,\nАлушта",
        "service": "БезкоштовнийWi-Fi,\nВласнийпляж,\nСпа/велнес"
    },
    "Аквілон3*": {
        "name": "Аквілон3*",
        "url": "https://www.turpravda.ua/uc/alupka/Akvilon-h23115.html",
        "rate": "8.1",
        "city": "Крим,\nАлушта",
        "service": "БезкоштовнийWi-Fi,\nВласнийпляж,\nСпа/велнес"
    },
    "ЛіхтаріГурзуфа2*": {
        "name": "ЛіхтаріГурзуфа2*",
        "url": "https://www.turpravda.ua/uc/gurzuf/Fonari_Gurzufa-h26445.html",
        "rate": "8.1",
        "city": "Крим,\nАлушта",
        "service": "БезкоштовнийWi-Fi,\nВласнийпляж,\nСпа/велнес"
    },
    "БухтаМрії3*": {
        "name": "БухтаМрії3*",
        "url": "https://www.turpravda.ua/uc/sevastopol/Buhta_Mechty-h29513.html",
        "rate": "8.1",
        "city": "Крим,\nАлушта",
        "service": "БезкоштовнийWi-Fi,\nВласнийпляж,\nСпа/велнес"
    },
    "ГостьовийбудинокГрей-S2*": {
        "name": "ГостьовийбудинокГрей-S2*",
        "url": "https://www.turpravda.ua/uc/feodosia/grej_s-h64196.html",
        "rate": "8.1",
        "city": "Крим,\nАлушта",
        "service": "БезкоштовнийWi-Fi,\nВласнийпляж,\nСпа/велнес"
    },
    "Олена2*": {
        "name": "Олена2*",
        "url": "https://www.turpravda.ua/uc/novyy_svet/Elena-h31460.html",
        "rate": "8.1",
        "city": "Крим,\nАлушта",
        "service": "БезкоштовнийWi-Fi,\nВласнийпляж,\nСпа/велнес"
    },
    "Лазурний3*": {
        "name": "Лазурний3*",
        "url": "https://www.turpravda.ua/uc/alushta/Lazurnyy8-h23037.html",
        "rate": "8.1",
        "city": "Крим,\nАлушта",
        "service": "БезкоштовнийWi-Fi,\nВласнийпляж,\nСпа/велнес"
    },
    "ПерлинаДракона1*": {
        "name": "ПерлинаДракона1*",
        "url": "https://www.turpravda.ua/uc/rybache/Zhemchuzhina_Drakona-h20845.html",
        "rate": "8.1",
        "city": "Крим,\nАлушта",
        "service": "БезкоштовнийWi-Fi,\nВласнийпляж,\nСпа/велнес"
    },
    "Триплюсдва2*": {
        "name": "Триплюсдва2*",
        "url": "https://www.turpravda.ua/uc/novyy_svet/Tri_pljus_dva-h26683.html",
        "rate": "8.1",
        "city": "Крим,\nАлушта",
        "service": "БезкоштовнийWi-Fi,\nВласнийпляж,\nСпа/велнес"
    },
    "ДеАЗ2*": {
        "name": "ДеАЗ2*",
        "url": "https://www.turpravda.ua/uc/kerch/DeAz-h19834.html",
        "rate": "8.1",
        "city": "Крим,\nАлушта",
        "service": "БезкоштовнийWi-Fi,\nВласнийпляж,\nСпа/велнес"
    },
    "Планета2*": {
        "name": "Планета2*",
        "url": "https://www.turpravda.ua/uc/evpatoria/Planeta-h14932.html",
        "rate": "8.1",
        "city": "Крим,\nАлушта",
        "service": "БезкоштовнийWi-Fi,\nВласнийпляж,\nСпа/велнес"
    },
    "Мустанг2*": {
        "name": "Мустанг2*",
        "url": "https://www.turpravda.ua/uc/kaciveli/Mustang-h21809.html",
        "rate": "8.1",
        "city": "Крим,\nАлушта",
        "service": "БезкоштовнийWi-Fi,\nВласнийпляж,\nСпа/велнес"
    },
    "ВіллаБлакитнаЗатока4*": {
        "name": "ВіллаБлакитнаЗатока4*",
        "url": "https://www.turpravda.ua/uc/simeiz/villa_goluboj_zaliv-h37577.html",
        "rate": "8.1",
        "city": "Крим,\nАлушта",
        "service": "БезкоштовнийWi-Fi,\nВласнийпляж,\nСпа/велнес"
    },
    "Утьос3*": {
        "name": "Утьос3*",
        "url": "https://www.turpravda.ua/uc/utes/Utes-h18829.html",
        "rate": "8.1",
        "city": "Крим,\nАлушта",
        "service": "БезкоштовнийWi-Fi,\nВласнийпляж,\nСпа/велнес"
    },
    "Мандарин1*": {
        "name": "Мандарин1*",
        "url": "https://www.turpravda.ua/uc/peschanoe/Mandarin-h24120.html",
        "rate": "8.1",
        "city": "Крим,\nАлушта",
        "service": "БезкоштовнийWi-Fi,\nВласнийпляж,\nСпа/велнес"
    },
    "Посмішка2*": {
        "name": "Посмішка2*",
        "url": "https://www.turpravda.ua/uc/evpatoria/Ulybka-h26613.html",
        "rate": "8.1",
        "city": "Крим,\nАлушта",
        "service": "БезкоштовнийWi-Fi,\nВласнийпляж,\nСпа/велнес"
    },
    "АпартаментиХерсонес3*": {
        "name": "АпартаментиХерсонес3*",
        "url": "https://www.turpravda.ua/uc/sevastopol/Apartamenty_Hersones-h18607.html",
        "rate": "8.1",
        "city": "Крим,\nАлушта",
        "service": "БезкоштовнийWi-Fi,\nВласнийпляж,\nСпа/велнес"
    },
    "ВіллаФорос3*": {
        "name": "ВіллаФорос3*",
        "url": "https://www.turpravda.ua/uc/foros/Villa_Foros-h31142.html",
        "rate": "8.1",
        "city": "Крим,\nАлушта",
        "service": "БезкоштовнийWi-Fi,\nВласнийпляж,\nСпа/велнес"
    },
    "Блакитнахвиля3*": {
        "name": "Блакитнахвиля3*",
        "url": "https://www.turpravda.ua/uc/alushta/Golubaja_volna-h10652.html",
        "rate": "8.1",
        "city": "Крим,\nАлушта",
        "service": "БезкоштовнийWi-Fi,\nВласнийпляж,\nСпа/велнес"
    }
}